<?xml version="1.0" encoding="UTF-8" standalone="yes"?>
<JPK xmlns="http://crd.gov.pl/wzor/2021/12/27/11149/" xmlns:ns2="http://crd.gov.pl/xml/schematy/dziedzinowe/mf/2021/06/08/eD/DefinicjeTypy/">
    <Naglowek>
        <KodFormularza kodSystemowy="JPK_V7K (2)" wersjaSchemy="1-0E">JPK_VAT</KodFormularza>
        <WariantFormularza>2</WariantFormularza>
        <DataWytworzeniaJPK>2023-04-24T20:26:54.963Z</DataWytworzeniaJPK>
        <NazwaSystemu>Taxman</NazwaSystemu>
        <CelZlozenia poz="P_7">2</CelZlozenia>
        <KodUrzedu>1436</KodUrzedu>
        <Rok>2023</Rok>
        <Miesiac>3</Miesiac>
    </Naglowek>
    <Podmiot1 rola="Podatnik">
        <OsobaFizyczna>
            <ns2:NIP>5262452071</ns2:NIP>
            <ns2:ImiePierwsze>Andrzej</ns2:ImiePierwsze>
            <ns2:Nazwisko>Wiśniewski</ns2:Nazwisko>
            <ns2:DataUrodzenia>1950-03-31</ns2:DataUrodzenia>
            <Email>brzaskun@o2.pl</Email>
            <Telefon>603133396</Telefon>
        </OsobaFizyczna>
    </Podmiot1>
    <Ewidencja>
        <SprzedazCtrl>
            <LiczbaWierszySprzedazy>0</LiczbaWierszySprzedazy>
            <PodatekNalezny>0</PodatekNalezny>
        </SprzedazCtrl>
        <ZakupCtrl>
            <LiczbaWierszyZakupow>0</LiczbaWierszyZakupow>
            <PodatekNaliczony>0</PodatekNaliczony>
        </ZakupCtrl>
    </Ewidencja>
</JPK>
